aicommit_cli/__init__.py
aicommit_cli/cli.py
aicommit_cli/core.py
aicommit_joy-0.1.2.dist-info/METADATA
aicommit_joy-0.1.2.dist-info/WHEEL
aicommit_joy-0.1.2.dist-info/entry_points.txt
aicommit_joy-0.1.2.dist-info/licenses/LICENSE
aicommit_joy-0.1.2.dist-info/RECORD
