Metadata-Version: 2.4
Name: aicommit-joy
Version: 0.1.2
Summary: AI-powered Git commit message generator using Conventional Commits
Author: Joy
License: MIT
License-File: LICENSE
Keywords: ai,aicommit,aicommit-cli,aicommitcli,autocommit,automate,automation,cli,commit,commits,conventional-commits,gemini,git,smartcommit
Classifier: Development Status :: 4 - Beta
Classifier: Environment :: Console
Classifier: Intended Audience :: Developers
Classifier: License :: OSI Approved :: MIT License
Classifier: Operating System :: OS Independent
Classifier: Programming Language :: Python :: 3
Classifier: Programming Language :: Python :: 3.10
Classifier: Programming Language :: Python :: 3.11
Classifier: Programming Language :: Python :: 3.12
Classifier: Topic :: Software Development :: Libraries :: Python Modules
Classifier: Topic :: Software Development :: Version Control :: Git
Requires-Python: >=3.10
Requires-Dist: google-genai>=0.2.2
Requires-Dist: python-dotenv>=1.0.0
